gkvalves/__init__.py
gkvalves/main.py
gkvalves/valves.py
gkvalves-1.0.2.dist-info/LICENSE
gkvalves-1.0.2.dist-info/METADATA
gkvalves-1.0.2.dist-info/WHEEL
gkvalves-1.0.2.dist-info/entry_points.txt
gkvalves-1.0.2.dist-info/top_level.txt
gkvalves-1.0.2.dist-info/RECORD
