Metadata-Version: 2.1
Name: gkvalves
Version: 1.0.2
Summary: Gorod Krovi valve step solver.
Author: Ivan Luengo
License: GNU GENERAL PUBLIC LICENSE
Project-URL: Source, https://github.com/luengoc/gkvalves/
Project-URL: Issues, https://github.com/luengoc/gkvalves/issues/
Classifier: Development Status :: 5 - Production/Stable
Classifier: License :: OSI Approved :: GNU General Public License v3 (GPLv3)
Classifier: Operating System :: OS Independent
Classifier: Programming Language :: Python :: 3 :: Only
Classifier: Programming Language :: Python :: 3.11
Classifier: Programming Language :: Python :: 3.12
Classifier: Topic :: Software Development :: Libraries :: Python Modules
Classifier: Topic :: Utilities
Classifier: Typing :: Typed
Requires-Python: >=3.11
License-File: LICENSE
Provides-Extra: dev
Requires-Dist: build <=1.2.1,>=0.10.0 ; extra == 'dev'
Requires-Dist: wheel <=0.43,>=0.36.2 ; extra == 'dev'
